cookiescope/__init__.py
cookiescope/cookies.py
cookiescope/main.py
cookiescope/utility.py
cookiescope/browsers/__init__.py
cookiescope/browsers/base.py
cookiescope/browsers/chrome.py
cookiescope/browsers/chrome_generic.py
cookiescope/browsers/chromium.py
cookiescope/browsers/edge.py
cookiescope/browsers/firefox.py
cookiescope/browsers/safari.py
cookiescope/decryptors/__init__.py
cookiescope/decryptors/base.py
cookiescope/decryptors/linux.py
cookiescope/decryptors/macos.py
cookiescope/decryptors/posix.py
cookiescope/decryptors/windows.py
cookiescope/extractors/__init__.py
cookiescope/extractors/binary.py
cookiescope/extractors/sqlite.py
cookiescope-0.0.2.dist-info/METADATA
cookiescope-0.0.2.dist-info/WHEEL
cookiescope-0.0.2.dist-info/entry_points.txt
cookiescope-0.0.2.dist-info/licenses/LICENSE
cookiescope-0.0.2.dist-info/RECORD
