Metadata-Version: 2.1
Name: cookiescope
Version: 0.0.2
Summary: Cookie inspector.
Project-URL: Homepage, https://github.com/wijjo/cookiescope
Author-email: Steve Cooper <steve@wijjo.com>
License-File: LICENSE
Classifier: License :: OSI Approved :: GNU General Public License v3 or later (GPLv3+)
Classifier: Operating System :: OS Independent
Classifier: Programming Language :: Python :: 3
Requires-Python: >=3.11
Requires-Dist: cryptography==41.0.5; sys_platform == 'darwin' or sys_platform == 'linux'
Requires-Dist: keyring==24.3.0; sys_platform == 'darwin' or sys_platform == 'linux'
Requires-Dist: pycryptodome==3.19.0; sys_platform == 'win32'
Requires-Dist: pypiwin32==223; sys_platform == 'win32'
Provides-Extra: build
Requires-Dist: build; extra == 'build'
